{
  "project_info": {
    "project_number": "517282639682",
    "project_id": "fireauth-2cbb0",
    "storage_bucket": "fireauth-2cbb0.appspot.com"
  },
  "client": [
    {
      "client_info": {
        "mobilesdk_app_id": "1:517282639682:android:220e867740114c90c7e2db",
        "android_client_info": {
          "package_name": "com.habit.help.habit_help"
        }
      },
      "oauth_client": [
        {
          "client_id": "517282639682-nn543tpoauquth11fmujc1vj2k3rqqes.apps.googleusercontent.com",
          "client_type": 3
        }
      ],
      "api_key": [
        {
          "current_key": "AIzaSyA33BNI5z_yv0xNg7nOVeWXNRe1uvQi3dg"
        }
      ],
      "services": {
        "appinvite_service": {
          "other_platform_oauth_client": [
            {
              "client_id": "517282639682-nn543tpoauquth11fmujc1vj2k3rqqes.apps.googleusercontent.com",
              "client_type": 3
            }
          ]
        }
      }
    }
  ],
  "configuration_version": "1"
}